BTrees/BTreeItemsTemplate.c
BTrees/BTreeModuleTemplate.c
BTrees/BTreeTemplate.c
BTrees/BucketTemplate.c
BTrees/Interfaces.py
BTrees/Length.py
BTrees/MergeTemplate.c
BTrees/SetOpTemplate.c
BTrees/SetOpTemplate.h
BTrees/SetTemplate.c
BTrees/TreeSetTemplate.c
BTrees/_IFBTree.c
BTrees/_IFBTree.cpython-313-darwin.so
BTrees/_IIBTree.c
BTrees/_IIBTree.cpython-313-darwin.so
BTrees/_IOBTree.c
BTrees/_IOBTree.cpython-313-darwin.so
BTrees/_IUBTree.c
BTrees/_IUBTree.cpython-313-darwin.so
BTrees/_LFBTree.c
BTrees/_LFBTree.cpython-313-darwin.so
BTrees/_LLBTree.c
BTrees/_LLBTree.cpython-313-darwin.so
BTrees/_LOBTree.c
BTrees/_LOBTree.cpython-313-darwin.so
BTrees/_LQBTree.c
BTrees/_LQBTree.cpython-313-darwin.so
BTrees/_OIBTree.c
BTrees/_OIBTree.cpython-313-darwin.so
BTrees/_OLBTree.c
BTrees/_OLBTree.cpython-313-darwin.so
BTrees/_OOBTree.c
BTrees/_OOBTree.cpython-313-darwin.so
BTrees/_OQBTree.c
BTrees/_OQBTree.cpython-313-darwin.so
BTrees/_OUBTree.c
BTrees/_OUBTree.cpython-313-darwin.so
BTrees/_QFBTree.c
BTrees/_QFBTree.cpython-313-darwin.so
BTrees/_QLBTree.c
BTrees/_QLBTree.cpython-313-darwin.so
BTrees/_QOBTree.c
BTrees/_QOBTree.cpython-313-darwin.so
BTrees/_QQBTree.c
BTrees/_QQBTree.cpython-313-darwin.so
BTrees/_UFBTree.c
BTrees/_UFBTree.cpython-313-darwin.so
BTrees/_UIBTree.c
BTrees/_UIBTree.cpython-313-darwin.so
BTrees/_UOBTree.c
BTrees/_UOBTree.cpython-313-darwin.so
BTrees/_UUBTree.c
BTrees/_UUBTree.cpython-313-darwin.so
BTrees/__init__.py
BTrees/_base.py
BTrees/_compat.py
BTrees/_datatypes.py
BTrees/_fsBTree.c
BTrees/_fsBTree.cpython-313-darwin.so
BTrees/_module_builder.py
BTrees/check.py
BTrees/floatvaluemacros.h
BTrees/intkeymacros.h
BTrees/intvaluemacros.h
BTrees/objectkeymacros.h
BTrees/objectvaluemacros.h
BTrees/sorters.c
BTrees/utils.py
BTrees/tests/__init__.py
BTrees/tests/_test_builder.py
BTrees/tests/common.py
BTrees/tests/testBTrees.py
BTrees/tests/testConflict.py
BTrees/tests/testPersistency.py
BTrees/tests/test_Length.py
BTrees/tests/test_OOBTree.py
btrees-6.3.dist-info/licenses/LICENSE.txt
btrees-6.3.dist-info/METADATA
btrees-6.3.dist-info/WHEEL
btrees-6.3.dist-info/top_level.txt
btrees-6.3.dist-info/RECORD
